{
  "step_type": "BGO",
  "step_number": 20000,
  "title": "BUSINESS - Business reconciliation validation - KBridge Source",
  "predecessor": "BGO-20000",
  "successor": "BGO-20000",
  "primary_team": "BUSINESS_CUTOVER",
  "impacted_teams": "",
  "macro_time_sequence": "G - WEEK-END 2 - P&amp;C",
  "time_sequence": "GO - BUSSINESS DATA ENTRIES",
  "task_list": [
    {
      "nominated_user": "",
      "instruction_assigned_team": "BUSINESS_CUTOVER",
      "instruction_title": "Business Validation for K+ - Atlas reconciliation - IRS",
      "associated_controls": "",
      "instruction_id": "BGO-20000-1"
    },
    {
      "nominated_user": "",
      "instruction_assigned_team": "BUSINESS_CUTOVER",
      "instruction_title": "Business Validation for K+ - Atlas reconciliation - Bonds",
      "associated_controls": "",
      "instruction_id": "BGO-20000-2"
    },
    {
      "nominated_user": "",
      "instruction_assigned_team": "BUSINESS_CUTOVER",
      "instruction_title": "Business Validation for K+ - Atlas reconciliation - FX Swap",
      "associated_controls": "",
      "instruction_id": "BGO-20000-3"
    },
    {
      "nominated_user": "",
      "instruction_assigned_team": "BUSINESS_CUTOVER",
      "instruction_title": "Business Validation for K+ - Atlas reconciliation - Cash Accounts",
      "associated_controls": "",
      "instruction_id": "BGO-20000-4"
    },
    {
      "nominated_user": "",
      "instruction_assigned_team": "BUSINESS_CUTOVER",
      "instruction_title": "Business Validation for K+ - Atlas reconciliation - BOE",
      "associated_controls": "",
      "instruction_id": "BGO-20000-5"
    },
    {
      "nominated_user": "",
      "instruction_assigned_team": "BUSINESS_CUTOVER",
      "instruction_title": "Business Validation for K+ - Atlas reconciliation - Repo",
      "associated_controls": "",
      "instruction_id": "BGO-20000-6"
    }
  ]
}
