{
  "step_type": "IGO",
  "step_number": 11725,
  "title": "SECLI GVA - CLIENTS CONFIDENTIAL &amp; SECRET DATA CHECKS",
  "predecessor": "IGO-11848",
  "successor": "TRT-13245",
  "primary_team": "SECLI",
  "impacted_teams": "",
  "macro_time_sequence": "",
  "time_sequence": "WEEK-END 1",
  "task_list": [
    {
      "nominated_user": "",
      "instruction_assigned_team": "SECLI",
      "instruction_title": "CLIENT INTEGRITY VERIFICATION\nCONTROL PRESENCE OF K&E FIELD VALUES AND PRE-REQUISITES OF MIFID, K&E, AML.",
      "associated_controls": "[ - ](#)",
      "instruction_id": "IGO-11725-1"
    }
  ]
}
