{
  "step_type": "PRE",
  "step_number": 15046,
  "title": "QUARTAL - Enable PR service",
  "predecessor": "PRE-15046",
  "successor": "PRE-15046",
  "primary_team": "QUARTAL",
  "impacted_teams": "",
  "macro_time_sequence": "G - WEEK-END 2 - P&amp;C",
  "time_sequence": "GU - RETURN TO BAU - INSTITUTIONAL TREATMENTS",
  "task_list": [
    {
      "nominated_user": "",
      "instruction_assigned_team": "QUARTAL",
      "instruction_title": "Enable PR service",
      "associated_controls": "",
      "instruction_id": "PRE-15046-1"
    }
  ]
}
