{
  "step_type": "PRE",
  "step_number": 9323,
  "title": "DOCUMENTUM - DÉMARRAGE IMPORT AVEC BACKUP ACTIF",
  "predecessor": "PRE-9097",
  "successor": "PRE-12133",
  "primary_team": "DOCUMENTUM",
  "impacted_teams": "",
  "macro_time_sequence": "",
  "time_sequence": "WEEK-END 2",
  "task_list": [
    {
      "nominated_user": "",
      "instruction_assigned_team": "DOCUMENTUM",
      "instruction_title": "DÉMARRAGE IMPORT AVEC BACKUP ACTIF",
      "associated_controls": "[ - ](#)",
      "instruction_id": "PRE-9323-1"
    }
  ]
}
