{
  "step_type": "PRE",
  "step_number": 14231,
  "title": "SPOC_INTEGRATION - DISABLE SECLI JOBS/ISOLATION on PROD-Like",
  "predecessor": "PRE-14231",
  "successor": "PRE-14231",
  "primary_team": "SPOC_INTEGRATION",
  "impacted_teams": "",
  "macro_time_sequence": "",
  "time_sequence": "WEEK-END 1",
  "task_list": [
    {
      "nominated_user": "",
      "instruction_assigned_team": "SPOC_INTEGRATION",
      "instruction_title": "To send \n\nPlease PUT ON HOLD AND DO NOT EXECUTE the SECLI Batch jobs (Except MIFID & EMIR) from Friday until Sunday on CSD Weekend 1, on PROD-Like\n\n\n\n\nThe Thursday EOD PROD BANK Batch for SECLI part should have been run as expected.",
      "associated_controls": "",
      "instruction_id": "PRE-14231-1"
    }
  ]
}
