{
  "step_type": "TRT",
  "step_number": 11394,
  "title": "CHECK COMPONENTS ALIGNMENT (PROD-LIKE) AND SANITY CHECKS BEFORE MIGRATION",
  "predecessor": "TRT-11394",
  "successor": "TRT-11394",
  "primary_team": "IT_ENV",
  "impacted_teams": "",
  "macro_time_sequence": "A - PREMIGRATION",
  "time_sequence": "AB - PROD LIKE ENV. PREPARATION",
  "task_list": [
    {
      "nominated_user": "-",
      "instruction_assigned_team": "IT_ENV",
      "instruction_title": "_- Deploy Last **PRODUCTION **PATCH FOR ALL APPLICATION IN SCOPE OF RUN/DR\n - - Check component alignment [Application to be in Iso Prod version + Hot fixes]\n\n_- Sanity checks [Check Environment space & temporary database table space] before migration on **PROD LIKE ENVIRONMENT**",
      "associated_controls": "",
      "instruction_id": "1"
    }
  ]
}
