{
  "step_type": "TRT",
  "step_number": 13912,
  "title": "SECLI LDN&amp;JRS - SEND TORIG FOR BASE TIERS PUBLIC",
  "predecessor": "TRT-11987",
  "successor": "TRT-11987",
  "primary_team": "SECLI",
  "impacted_teams": "",
  "macro_time_sequence": "C - WEEK-END 1 - CSD",
  "time_sequence": "CN - SENDING OF CLIENTS TO ATLAS - PROD LIKE ENV.",
  "task_list": [
    {
      "nominated_user": "",
      "instruction_assigned_team": "SECLI",
      "instruction_title": "SENDING ALL STEP -  SECLI GVA - SEND TORIG FOR BASE TIERS PUBLIC",
      "associated_controls": "[ - ](#)",
      "instruction_id": "TRT-13912-1"
    },
    {
      "nominated_user": "",
      "instruction_assigned_team": "SECLI",
      "instruction_title": "TORIG reception verification in Base Tiers Public",
      "associated_controls": "[ - ](#)",
      "instruction_id": "TRT-13912-2"
    },
    {
      "nominated_user": "",
      "instruction_assigned_team": "SECLI",
      "instruction_title": "Check the logs\nReport the defect via Jira",
      "associated_controls": "[ - ](#)",
      "instruction_id": "TRT-13912-3"
    }
  ]
}
